examples/__init__.py
pylantool/__init__.py
pylantool/logger.py
pylantool/decorator/__init__.py
pylantool/decorator/_lazy_property.py
pylantool/fs/__init__.py
pylantool/fs/_core.py
pylantool/fs/_virtual_directory.py
pylantool/io/__init__.py
pylantool/io/_core.py
pylantool/profiler/__init__.py
pylantool/profiler/_timer.py
tests/__init__.py
tests/test_decorators.py
tests/test_fs.py
tests/test_logger.py
pylantool-0.1.0.0.dist-info/LICENSE
pylantool-0.1.0.0.dist-info/METADATA
pylantool-0.1.0.0.dist-info/WHEEL
pylantool-0.1.0.0.dist-info/top_level.txt
pylantool-0.1.0.0.dist-info/RECORD
