Metadata-Version: 2.1
Name: pylantool
Version: 0.1.0.0
Summary: A collection of functions common used in python programing
Home-page: https://gitee.com/mysticalwing/pylantool
Author: qin_hw
Author-email: 1039954093@qq.com
License: UNKNOWN
Platform: UNKNOWN
Classifier: Natural Language :: English
Classifier: Operating System :: POSIX :: Linux
Classifier: Programming Language :: Python
Classifier: Programming Language :: Python :: 3.6
Classifier: Programming Language :: Python :: Implementation :: CPython
Requires-Python: >=3.6
